{"assets":[],"layers":[{"ddd":0,"ind":0,"ty":4,"nm":"DESIGN","parent":1,"ks":{"o":{"k":100},"r":{"k":0},"p":{"k":[0,0,0]},"a":{"k":[0,0,0]},"s":{"k":[{"i":{"x":[0.25,0.25,0.25],"y":[1,1,0.25]},"o":{"x":[0.75,0.75,0.75],"y":[0,0,0.75]},"n":["0p25_1_0p75_0","0p25_1_0p75_0","0p25_0p25_0p75_0p75"],"t":0,"s":[50,50,100],"e":[132,132,100]},{"i":{"x":[0.25,0.25,0.25],"y":[1,1,0.25]},"o":{"x":[0.75,0.75,0.75],"y":[0,0,0.75]},"n":["0p25_1_0p75_0","0p25_1_0p75_0","0p25_0p25_0p75_0p75"],"t":25,"s":[132,132,100],"e":[50,50,100]},{"i":{"x":[0.25,0.25,0.25],"y":[1,1,0.25]},"o":{"x":[0.75,0.75,0.75],"y":[0,0,0.75]},"n":["0p25_1_0p75_0","0p25_1_0p75_0","0p25_0p25_0p75_0p75"],"t":50,"s":[50,50,100],"e":[132,132,100]},{"i":{"x":[0.25,0.25,0.25],"y":[1,1,0.25]},"o":{"x":[0.75,0.75,0.75],"y":[0,0,0.75]},"n":["0p25_1_0p75_0","0p25_1_0p75_0","0p25_0p25_0p75_0p75"],"t":75,"s":[132,132,100],"e":[50,50,100]},{"i":{"x":[0.25,0.25,0.25],"y":[1,1,0.25]},"o":{"x":[0.75,0.75,0.75],"y":[0,0,0.75]},"n":["0p25_1_0p75_0","0p25_1_0p75_0","0p25_0p25_0p75_0p75"],"t":100,"s":[50,50,100],"e":[132,132,100]},{"i":{"x":[0.25,0.25,0.25],"y":[1,1,0.25]},"o":{"x":[0.75,0.75,0.75],"y":[0,0,0.75]},"n":["0p25_1_0p75_0","0p25_1_0p75_0","0p25_0p25_0p75_0p75"],"t":125,"s":[132,132,100],"e":[50,50,100]},{"i":{"x":[0.25,0.25,0.25],"y":[1,1,0.25]},"o":{"x":[0.75,0.75,0.75],"y":[0,0,0.75]},"n":["0p25_1_0p75_0","0p25_1_0p75_0","0p25_0p25_0p75_0p75"],"t":150,"s":[50,50,100],"e":[132,132,100]},{"i":{"x":[0.25,0.25,0.25],"y":[1,1,0.25]},"o":{"x":[0.75,0.75,0.75],"y":[0,0,0.75]},"n":["0p25_1_0p75_0","0p25_1_0p75_0","0p25_0p25_0p75_0p75"],"t":175,"s":[132,132,100],"e":[50,50,100]},{"i":{"x":[0.25,0.25,0.25],"y":[1,1,0.25]},"o":{"x":[0.75,0.75,0.75],"y":[0,0,0.75]},"n":["0p25_1_0p75_0","0p25_1_0p75_0","0p25_0p25_0p75_0p75"],"t":200,"s":[50,50,100],"e":[132,132,100]},{"i":{"x":[0.25,0.25,0.25],"y":[1,1,0.25]},"o":{"x":[0.75,0.75,0.75],"y":[0,0,0.75]},"n":["0p25_1_0p75_0","0p25_1_0p75_0","0p25_0p25_0p75_0p75"],"t":225,"s":[132,132,100],"e":[100,100,100]},{"t":250}]}},"ao":0,"shapes":[{"d":1,"ty":"el","s":{"k":[271,271]},"p":{"k":[0,0]},"nm":"Ellipse Path 1","mn":"ADBE Vector Shape - Ellipse"},{"ty":"fl","fillEnabled":true,"c":{"k":[0.51,1,0,1]},"o":{"k":100},"nm":"Fill 1","mn":"ADBE Vector Graphic - Fill"}],"ip":0,"op":250,"st":0,"bm":0,"sr":1},{"ddd":0,"ind":1,"ty":4,"nm":"#button .button","ln":"button","cl":"button","ks":{"o":{"k":100},"r":{"k":0},"p":{"k":[{"i":{"x":0.833,"y":0.833},"o":{"x":0.72,"y":0.72},"n":"0p833_0p833_0p72_0p72","t":0,"s":[540,960,0],"e":[540,960,0],"to":[0,0,0],"ti":[0,0,0]},{"i":{"x":0,"y":1},"o":{"x":0.72,"y":0},"n":"0_1_0p72_0","t":25,"s":[540,960,0],"e":[124,410,0],"to":[0,0,0],"ti":[0,0,0]},{"i":{"x":0,"y":1},"o":{"x":1,"y":0},"n":"0_1_1_0","t":44,"s":[124,410,0],"e":[888,1288,0],"to":[0,0,0],"ti":[0,0,0]},{"i":{"x":0,"y":1},"o":{"x":1,"y":0},"n":"0_1_1_0","t":64.177,"s":[888,1288,0],"e":[286,1294,0],"to":[0,0,0],"ti":[0,0,0]},{"i":{"x":0,"y":1},"o":{"x":1,"y":0},"n":"0_1_1_0","t":93,"s":[286,1294,0],"e":[790,524,0],"to":[0,0,0],"ti":[0,0,0]},{"i":{"x":0,"y":1},"o":{"x":1,"y":0},"n":"0_1_1_0","t":122,"s":[790,524,0],"e":[500,1266,0],"to":[0,0,0],"ti":[0,0,0]},{"i":{"x":0,"y":1},"o":{"x":1,"y":0},"n":"0_1_1_0","t":149,"s":[500,1266,0],"e":[432,1542,0],"to":[0,0,0],"ti":[0,0,0]},{"i":{"x":0,"y":1},"o":{"x":1,"y":0},"n":"0_1_1_0","t":168,"s":[432,1542,0],"e":[444,204,0],"to":[0,0,0],"ti":[0,0,0]},{"i":{"x":0,"y":1},"o":{"x":1,"y":0},"n":"0_1_1_0","t":198,"s":[444,204,0],"e":[916,282,0],"to":[0,0,0],"ti":[0,0,0]},{"i":{"x":0,"y":1},"o":{"x":1,"y":0},"n":"0_1_1_0","t":218,"s":[916,282,0],"e":[540,960,0],"to":[0,0,0],"ti":[0,0,0]},{"t":250}]},"a":{"k":[0,0,0]},"s":{"k":[{"i":{"x":[0.29,0.29,0.29],"y":[1,1,0.29]},"o":{"x":[0.71,0.71,0.71],"y":[0,0,0.71]},"n":["0p29_1_0p71_0","0p29_1_0p71_0","0p29_0p29_0p71_0p71"],"t":0,"s":[0,0,100],"e":[110,110,100]},{"i":{"x":[0.29,0.29,0.29],"y":[1,1,0.29]},"o":{"x":[0.71,0.71,0.71],"y":[0,0,0.71]},"n":["0p29_1_0p71_0","0p29_1_0p71_0","0p29_0p29_0p71_0p71"],"t":13,"s":[110,110,100],"e":[100,100,100]},{"t":25}]}},"ao":0,"shapes":[{"d":1,"ty":"el","s":{"k":[271,271]},"p":{"k":[0,0]},"nm":"Ellipse Path 1","mn":"ADBE Vector Shape - Ellipse"},{"ty":"fl","fillEnabled":true,"c":{"k":[1,0,0,1]},"o":{"k":100},"nm":"Fill 1","mn":"ADBE Vector Graphic - Fill"}],"ip":0,"op":250,"st":0,"bm":0,"sr":1},{"ddd":0,"ind":2,"ty":4,"nm":"background","ks":{"o":{"k":100},"r":{"k":0},"p":{"k":[540,960,0]},"a":{"k":[0,0,0]},"s":{"k":[100,100,100]}},"ao":0,"shapes":[{"ty":"rc","d":1,"s":{"k":[1080,1920]},"p":{"k":[0,0]},"r":{"k":0},"nm":"Rectangle Path 1","mn":"ADBE Vector Shape - Rect"},{"ty":"fl","fillEnabled":true,"c":{"k":[1,1,1,1]},"o":{"k":100},"nm":"Fill 1","mn":"ADBE Vector Graphic - Fill"}],"ip":0,"op":250,"st":0,"bm":0,"sr":1}],"v":"4.5.3","ddd":0,"ip":0,"op":250,"fr":25,"w":1080,"h":1920}